xrag/__init__.py
xrag-0.0.0.dist-info/METADATA
xrag-0.0.0.dist-info/WHEEL
xrag-0.0.0.dist-info/top_level.txt
xrag-0.0.0.dist-info/RECORD
