Metadata-Version: 2.1
Name: xrag
Version: 0.0.0
Summary: Coming Soon
Author-email: Dmitriy Leybel <dmleybel@gmail.com>
